fastapi_injector/__init__.py
fastapi_injector/attach.py
fastapi_injector/exceptions.py
fastapi_injector/injected.py
fastapi_injector/py.typed
fastapi_injector/request_scope.py
fastapi_injector-0.9.0.dist-info/METADATA
fastapi_injector-0.9.0.dist-info/WHEEL
fastapi_injector-0.9.0.dist-info/licenses/LICENSE
fastapi_injector-0.9.0.dist-info/RECORD
