Metadata-Version: 2.4
Name: fastapi-injector
Version: 0.9.0
Summary: python-injector integration for FastAPI
License: BSD
License-File: LICENSE
Author: Matyas Richter
Author-email: matyas@mrichter.cz
Requires-Python: >=3.10,<4
Classifier: Topic :: Software Development :: Libraries
Classifier: Framework :: FastAPI
Classifier: Environment :: Web Environment
Classifier: Intended Audience :: Developers
Classifier: Typing :: Typed
Provides-Extra: slim
Provides-Extra: standard
Requires-Dist: fastapi (>=0.70.0) ; extra == "standard"
Requires-Dist: fastapi-slim (>=0.111.0) ; extra == "slim"
Requires-Dist: injector (>=0.19.0)
